symetrics/__init__.py
symetrics/dbcontext.py
symetrics/modelcontext.py
symetrics/symetrics_api.py
symetrics/src/__init__.py
symetrics/src/datastruct.py
symetrics-19.0.0.dist-info/METADATA
symetrics-19.0.0.dist-info/WHEEL
symetrics-19.0.0.dist-info/top_level.txt
symetrics-19.0.0.dist-info/RECORD
