Metadata-Version: 2.1
Name: symetrics
Version: 19.0.0
Summary: SyMetrics API
Home-page: https://lbundalian.github.io/symetrics/
Author: Linnaeus Bundalian
Author-email: linnaeusbundalian@gmail.com
Keywords: python,synonymous variants
Classifier: Development Status :: 3 - Alpha
Classifier: Intended Audience :: Education
Classifier: Programming Language :: Python :: 2
Classifier: Programming Language :: Python :: 3
Classifier: Operating System :: MacOS :: MacOS X
Classifier: Operating System :: Microsoft :: Windows
Requires-Dist: numpy (==1.24.4)
Requires-Dist: pandas (==2.0.2)
Requires-Dist: scikit-learn (==1.2.2)
